odoo/addons/storage_backend_s3/README.rst
odoo/addons/storage_backend_s3/__init__.py
odoo/addons/storage_backend_s3/__manifest__.py
odoo/addons/storage_backend_s3/components/__init__.py
odoo/addons/storage_backend_s3/components/s3_adapter.py
odoo/addons/storage_backend_s3/i18n/storage_backend_s3.pot
odoo/addons/storage_backend_s3/models/__init__.py
odoo/addons/storage_backend_s3/models/storage_backend.py
odoo/addons/storage_backend_s3/static/description/icon.png
odoo/addons/storage_backend_s3/tests/__init__.py
odoo/addons/storage_backend_s3/tests/test_amazon_s3.py
odoo/addons/storage_backend_s3/tests/cassettes/AmazonS3Case.test_setting_and_getting_data_from_dir.yaml
odoo/addons/storage_backend_s3/tests/cassettes/AmazonS3Case.test_setting_and_getting_data_from_root.yaml
odoo/addons/storage_backend_s3/views/backend_storage_view.xml
odoo13_addon_storage_backend_s3-13.0.1.2.0.dist-info/METADATA
odoo13_addon_storage_backend_s3-13.0.1.2.0.dist-info/WHEEL
odoo13_addon_storage_backend_s3-13.0.1.2.0.dist-info/top_level.txt
odoo13_addon_storage_backend_s3-13.0.1.2.0.dist-info/RECORD
